nflpocketarea2023/__init__.py
nflpocketarea2023/metrics/__init__.py
nflpocketarea2023/metrics/pocket_area/__init__.py
nflpocketarea2023/metrics/pocket_area/all.py
nflpocketarea2023/metrics/pocket_area/base.py
nflpocketarea2023/metrics/pocket_area/helpers.py
nflpocketarea2023/metrics/pocket_area/helpers_test.py
nflpocketarea2023/metrics/pocket_area/passer_radius_area.py
nflpocketarea2023/metrics/pocket_area/passer_radius_area_test.py
nflpocketarea2023/metrics/pocket_area/pocket_pb_ch_area.py
nflpocketarea2023/metrics/pocket_area/pocket_pb_ch_area_test.py
nflpocketarea2023/metrics/pocket_area/rushers_pocket_area.py
nflpocketarea2023/metrics/pocket_area/rushers_pocket_area_test.py
nflpocketarea2023/metrics/pocket_area/voronoi_pocket_area.py
nflpocketarea2023/metrics/pocket_area/voronoi_pocket_area_test.py
nflpocketarea2023/pipeline/__init__.py
nflpocketarea2023/pipeline/flows/__init__.py
nflpocketarea2023/pipeline/flows/main.py
nflpocketarea2023/pipeline/tasks/__init__.py
nflpocketarea2023/pipeline/tasks/constants.py
nflpocketarea2023/pipeline/tasks/dataframes.py
nflpocketarea2023/pipeline/tasks/dataframes_test.py
nflpocketarea2023/pipeline/tasks/eligibility.py
nflpocketarea2023/pipeline/tasks/eligibility_test.py
nflpocketarea2023/pipeline/tasks/events.py
nflpocketarea2023/pipeline/tasks/events_test.py
nflpocketarea2023/pipeline/tasks/frames.py
nflpocketarea2023/pipeline/tasks/frames_test.py
nflpocketarea2023/pipeline/tasks/play_metrics.py
nflpocketarea2023/pipeline/tasks/play_metrics_test.py
nflpocketarea2023/pipeline/tasks/play_windows.py
nflpocketarea2023/pipeline/tasks/play_windows_test.py
nflpocketarea2023/pipeline/tasks/pocket_area.py
nflpocketarea2023/pipeline/tasks/pocket_area_test.py
nflpocketarea2023/pipeline/tasks/test_helpers.py
nflpocketarea2023/pipeline/tasks/test_helpers_test.py
nflpocketarea2023/pipeline/tasks/tracking.py
nflpocketarea2023/pipeline/tasks/tracking_test.py
nflpocketarea2023/visualization/__init__.py
nflpocketarea2023-0.0.8.dist-info/LICENSE
nflpocketarea2023-0.0.8.dist-info/METADATA
nflpocketarea2023-0.0.8.dist-info/WHEEL
nflpocketarea2023-0.0.8.dist-info/top_level.txt
nflpocketarea2023-0.0.8.dist-info/RECORD
