Metadata-Version: 2.1
Name: nflpocketarea2023
Version: 0.0.8
Summary: NFL Big Data Bowl 2023: Analyzing pocket area.
Author-email: Vinesh Kannan <v@hawk.iit.edu>, Tabor Alemu <talemu@hawk.iit.edu>, Alek Popovic <apopovic@hawk.iit.edu>
Project-URL: Homepage, https://github.com/vingkan/nflbigdatabowl2023
Classifier: Programming Language :: Python :: 3
Classifier: License :: OSI Approved :: MIT License
Classifier: Operating System :: OS Independent
Requires-Python: >=3.7
License-File: LICENSE
Requires-Dist: dacite (~=1.7.0)
Requires-Dist: matplotlib (~=3.5.3)
Requires-Dist: numpy (~=1.19.1)
Requires-Dist: pandas (~=1.3.5)
Requires-Dist: Pillow (~=9.4.0)
Requires-Dist: prefect (~=2.7.4)
Requires-Dist: requests (~=2.28.1)
Requires-Dist: seaborn (~=0.12.2)
Requires-Dist: scipy (~=1.6.3)
Requires-Dist: shapely (~=2.0.0)
